setup.py
cds_utils/__init__.py
cds_utils.egg-info/PKG-INFO
cds_utils.egg-info/SOURCES.txt
cds_utils.egg-info/dependency_links.txt
cds_utils.egg-info/top_level.txt