Metadata-Version: 1.0
Name: cds-utils
Version: 0.0.4
Summary: 图灵CDS工具类
Home-page: UNKNOWN
Author: hc
Author-email: huangcheng_cc@sina.com
License: MIT License
Keywords: 图灵CDS,工具类
Platform: any
